cli.py
config_menu.py
semantic_firewall.py
semfire.py
aegis/__init__.py
detectors/__init__.py
detectors/crescendo_escalation.py
detectors/echo_chamber.py
detectors/heuristic_detector.py
detectors/injection_detector.py
detectors/llm_provider.py
detectors/rule_based.py
detectors/__pycache__/__init__.cpython-311.pyc
detectors/__pycache__/rule_based.cpython-311.pyc
semfire-0.5.1.dist-info/licenses/LICENSE
semfire-0.5.1.dist-info/METADATA
semfire-0.5.1.dist-info/WHEEL
semfire-0.5.1.dist-info/entry_points.txt
semfire-0.5.1.dist-info/top_level.txt
semfire-0.5.1.dist-info/RECORD
